odoo/addons/currency_rate_inverted/README.rst
odoo/addons/currency_rate_inverted/__init__.py
odoo/addons/currency_rate_inverted/__manifest__.py
odoo/addons/currency_rate_inverted/models/__init__.py
odoo/addons/currency_rate_inverted/models/res_currency.py
odoo/addons/currency_rate_inverted/static/description/icon.png
odoo/addons/currency_rate_inverted/views/res_currency_view.xml
odoo11_addon_currency_rate_inverted-11.0.1.0.0.dist-info/DESCRIPTION.rst
odoo11_addon_currency_rate_inverted-11.0.1.0.0.dist-info/METADATA
odoo11_addon_currency_rate_inverted-11.0.1.0.0.dist-info/RECORD
odoo11_addon_currency_rate_inverted-11.0.1.0.0.dist-info/WHEEL
odoo11_addon_currency_rate_inverted-11.0.1.0.0.dist-info/metadata.json
odoo11_addon_currency_rate_inverted-11.0.1.0.0.dist-info/top_level.txt
